haystack_studio/__init__.py
haystack_studio-0.0.1.dist-info/METADATA
haystack_studio-0.0.1.dist-info/WHEEL
haystack_studio-0.0.1.dist-info/RECORD
