Metadata-Version: 2.3
Name: haystack-studio
Version: 0.0.1
Project-URL: Documentation, https://github.com/
Project-URL: Source, https://github.com/
Author-email: MJMcM <a@b.c>
Classifier: Development Status :: 4 - Beta
Classifier: Programming Language :: Python
Classifier: Programming Language :: Python :: 3.8
Classifier: Programming Language :: Python :: 3.9
Classifier: Programming Language :: Python :: 3.10
Classifier: Programming Language :: Python :: 3.11
Classifier: Programming Language :: Python :: 3.12
Classifier: Programming Language :: Python :: Implementation :: CPython
Requires-Python: >=3.8
Requires-Dist: haystack-ai
